packpath/__init__.py
packpath/__main__.py
packpath/test.py
packpath-0.9.4.dist-info/AUTHORS
packpath-0.9.4.dist-info/LICENSE
packpath-0.9.4.dist-info/METADATA
packpath-0.9.4.dist-info/WHEEL
packpath-0.9.4.dist-info/entry_points.txt
packpath-0.9.4.dist-info/top_level.txt
packpath-0.9.4.dist-info/RECORD
