Metadata-Version: 2.1
Name: packpath
Version: 0.9.4
Summary: Automatically upload Signal stickers from a given path and YAML configuration
Home-page: https://github.com/diegoe/packpath
Author: Diego Escalante Urrelo
Author-email: diegoe@gnome.org
License: AGPL-3.0-only
Project-URL: GitHub, https://github.com/diegoe/packpath
Platform: UNKNOWN
Classifier: Development Status :: 4 - Beta
Classifier: Environment :: Console
Classifier: Intended Audience :: End Users/Desktop
Classifier: License :: OSI Approved :: GNU Affero General Public License v3
Classifier: Programming Language :: Python :: 3.9
Classifier: Programming Language :: Python
Classifier: Topic :: Communications :: Chat
Classifier: Topic :: Utilities
Requires-Dist: signalstickers-client (>=3.1.0)
Requires-Dist: PyYAML (>=5.4.1)
